package_python_hello_world/__init__.py
package_python_hello_world-0.0.1.dist-info/METADATA
package_python_hello_world-0.0.1.dist-info/WHEEL
package_python_hello_world-0.0.1.dist-info/top_level.txt
package_python_hello_world-0.0.1.dist-info/RECORD
