Metadata-Version: 2.1
Name: package-python-hello-world
Version: 0.0.1
Summary: package python hello world
Home-page: UNKNOWN
Author: flaviogf
Author-email: flavio@smn.com.br
License: UNKNOWN
Platform: UNKNOWN
